shifrtranslator.py
shifrtranslator-1.0.0.dist-info/WHEEL
shifrtranslator-1.0.0.dist-info/METADATA
shifrtranslator-1.0.0.dist-info/RECORD
