Metadata-Version: 2.1
Name: shifrtranslator
Version: 1.0.0
Summary: Module for translating English text into: Morse code, Atbash cipher, Caesar cipher and Binary code
Author: Pavel Popov
Author-email: p16.popov@gmail.com
Requires-Python: >=3.6,<4.0
Classifier: Programming Language :: Python :: 3
Classifier: Programming Language :: Python :: 3.6
Classifier: Programming Language :: Python :: 3.7
Classifier: Programming Language :: Python :: 3.8
